AUTHORS.rst
CONTRIBUTING.rst
HISTORY.rst
LICENSE
MANIFEST.in
README.rst
setup.cfg
setup.py
analystnotes/__init__.py
analystnotes/filters.py
analystnotes/models.py
analystnotes/permissions.py
analystnotes/serializers.py
analystnotes/urls.py
analystnotes/validators.py
analystnotes/views.py
analystnotes/static/css/analystnotes.css
analystnotes/static/js/analystnotes.js
analystnotes/templates/analystnotes/base.html
analystnotes/templates/analystnotes/cmd.html
django_analystnotes.egg-info/PKG-INFO
django_analystnotes.egg-info/SOURCES.txt
django_analystnotes.egg-info/dependency_links.txt
django_analystnotes.egg-info/not-zip-safe
django_analystnotes.egg-info/top_level.txt