Metadata-Version: 1.1
Name: django-analystnotes
Version: 0.1.0
Summary: Security analyst notes.
Home-page: https://github.com/jpleger/django-analystnotes
Author: django-analystnotes
Author-email: james.pleger@riskiq.net
License: BSD
Keywords: django-analystnotes
Platform: UNKNOWN
Classifier: Development Status :: 2 - Pre-Alpha
Classifier: Framework :: Django
Classifier: Intended Audience :: Developers
Classifier: License :: OSI Approved :: BSD License
Classifier: Natural Language :: English
Classifier: Programming Language :: Python :: 2
Classifier: Programming Language :: Python :: 2.6
Classifier: Programming Language :: Python :: 2.7
Classifier: Programming Language :: Python :: 3
Classifier: Programming Language :: Python :: 3.3
